avaandmed/__init__.py
avaandmed/api_resources/__init__.py
avaandmed/api_resources/datasets/__init__.py
avaandmed/api_resources/datasets/dataset.py
avaandmed/api_resources/datasets/dataset_repository.py
avaandmed/api_resources/entities/__init__.py
avaandmed/api_resources/organizations/__init__.py
avaandmed/api_resources/organizations/my_organization.py
avaandmed/api_resources/organizations/organization.py
avaandmed/api_resources/organizations/organization_user.py
avaandmed/api_resources/users/__init__.py
avaandmed/api_resources/users/me.py
avaandmed/api_resources/users/user.py
avaandmed/exceptions/__init__.py
avaandmed/http/__init__.py
avaandmed/http/http_client.py
avaandmed/utils/__init__.py
avaandmed-0.5.0.dist-info/LICENSE
avaandmed-0.5.0.dist-info/METADATA
avaandmed-0.5.0.dist-info/WHEEL
avaandmed-0.5.0.dist-info/top_level.txt
avaandmed-0.5.0.dist-info/RECORD
