Metadata-Version: 2.1
Name: avaandmed
Version: 0.5.0
Summary: Python library for Avaandmed(Open Data) portal API
Home-page: https://github.com/Michanix/avaandmed-py
Author: Mihhail Matišinets
Author-email: mihhail.matisinets@gmail.com
License: UNKNOWN
Platform: UNKNOWN
Classifier: Development Status :: 3 - Alpha
Classifier: Intended Audience :: Developers
Classifier: Topic :: Software Development :: Libraries :: Python Modules
Classifier: License :: OSI Approved :: MIT License
Classifier: Programming Language :: Python :: 3
Classifier: Programming Language :: Python :: 3.6
Classifier: Programming Language :: Python :: 3.7
Classifier: Programming Language :: Python :: 3.8
Classifier: Programming Language :: Python :: 3.9
Requires-Python: >=3.6, <4
License-File: LICENSE
Requires-Dist: requests (>=2.25)
Requires-Dist: pydantic (>=1.8)
